[
    {
        "Subject": "CAAM 3XX",
        "Major": "CAAM, Pre-Med, Pre-Grad",
        "Minor": "BIOC, DSCI",
        "Name": "[HEAD] Anthony (Min) Kang",
        "Email": "amk17@",
		"OfficeHours": "TBA",
		"GradYear": "Sr."
    },
    {
        "Subject": "CHEM 211/212",
        "Major": "CHEM, BIOC, Pre-Med",
        "Name": "[HEAD] Eliot Behr",
        "Email": "eib2@",
        "OfficeHours": "TBA",
        "GradYear": "Jr."
    },
    {
        "Subject": "D2 Writing",
        "Major": "PSYC, Pre-Grad",
        "Minor": "STAT",
        "Name": "[HEAD] Andreas Weyland",
        "Email": "ahw2@",
        "OfficeHours": "TBA",
        "GradYear": "Sr."
    },
    {
        "Subject": "BIOS",
        "Major": "BIOC, Pre-Med",
        "Name": "Arvind Ramesh",
        "Email": "avr8@",
        "OfficeHours": "TBA",
        "GradYear": "Jr."
    },
        {
        "Subject": "BIOS",
        "Major": "SMEP, Pre-Med",
        "Minor": "BIOC",
        "Name": "Truman Archer",
        "Email": "tsa5@",
        "OfficeHours": "TBA",
        "GradYear": "Jr."
    },
        {
        "Subject": "BIOS 201/CHEM 211",
        "Major": "BIOS, Pre-Med",
        "Name": "Adam He",
        "Email": "aqh1@",
        "OfficeHours": "TBA",
        "GradYear": "So."
    },
    {
        "Subject": "CHEM 121/122",
        "Major": "BIOS, Pre-Med",
        "Name": "Sai Govindu",
        "Email": "srg10@",
        "OfficeHours": "TBA",
        "GradYear": "Jr."
    },
    {
        "Subject": "CHEM 211/212",
        "Major": "BIOC, Pre-Med",
        "Name": "Ananda Nandigam",
        "Email": "aln7@",
        "OfficeHours": "TBA",
        "GradYear": "Jr."
    },
    {
        "Subject": "CHEM 211/212",
        "Major": "BIOC, Pre-Med",
        "Name": "Aaron Lin",
        "Email": "ajl15@",
        "OfficeHours": "TBA",
        "GradYear": "Jr."
    },
    {
        "Subject": "D1/D3 Writing",
        "Major": "BIOC, ENGL, Pre-Med",
        "Name": "Syed Shams",
        "Email": "sss13@",
        "OfficeHours": "TBA",
        "GradYear": "Sr."
    },
    {
        "Subject": "ECON",
        "Major": "ECON, Pre-Med",
        "Minor": "BIOC",
        "Name": "Jacob Doddridge",
        "Email": "jrd14@",
        "OfficeHours": "TBA",
        "GradYear": "Sr."
    },
    {
        "Subject": "LING, PHIL, D1 Writing",
        "Major": "LING, PHIL, Pre-Law, Pre-Grad",
        "Minor": "PLST",
        "Name": "Amanda Lopatin",
        "Email": "ael8@",
        "OfficeHours": "TBA",
        "GradYear": "Sr."
    },
    {
        "Subject": "MATH 101/102",
        "Major": "MECH",
        "Minor": "Entrepreneurship, Eng. Design",
        "Name": "Reece Lusich",
        "Email": "rel5@",
        "OfficeHours": "TBA",
        "GradYear": "So."
    },
    {
        "Subject": "MATH 211/212/355",
        "Major": "COMP",
        "Minor": "MATH",
        "Name": "Lauren Ivory",
        "Email": "lni1@",
        "OfficeHours": "TBA",
        "GradYear": "Sr."
    },
    {
        "Subject": "MUSI",
        "Major": "MUSI",
        "Name": "Lucas Lemonholm",
        "Email": "lel8@",
        "OfficeHours": "TBA",
        "GradYear": "Sr."
    },
    {
        "Subject": "PHYS 101/102",
        "Major": "ELEC",
        "Minor": "RCEL",
        "Name": "Daniel Rothfusz",
        "Email": "dpr7@",
        "OfficeHours": "TBA",
        "GradYear": "Sr."
    },
    {
        "Subject": "POLI/SOPA",
        "Major": "POLI, SOPA, Pre-Grad",
        "Minor": "DSCI",
        "Name": "Mason Reece",
        "Email": "mpr9@",
		"OfficeHours": "TBA",
		"GradYear": "Sr."
    },
    {
        "Subject": "PSYC",
        "Major": "MANA, CGCI",
        "Name": "Vickie Liu",
        "Email": "vl9@",
		"OfficeHours": "TBA",
		"GradYear": "Sr."
    },
    {
        "Subject": "STAT",
        "Major": "STAT, COMP, Pre-Grad",
        "Name": "Zach Rewolinski",
        "Email": "ztr2@",
		"OfficeHours": "TBA",
		"GradYear": "Jr."
    }
]